testing/inject_multicast.py
testing/inject_udp.py
testing/multicast_listener.py
testing/simulant.py
wfdlogger/__init__.py
wfdlogger/__main__.py
wfdlogger/data/JetBrainsMono-Regular.ttf
wfdlogger/data/MASTER.SCP
wfdlogger/data/cwmacros.txt
wfdlogger/data/dialog.ui
wfdlogger/data/k6gte-wfdlogger.desktop
wfdlogger/data/k6gte-wfdlogger.png
wfdlogger/data/main.ui
wfdlogger/data/secname.json
wfdlogger/data/secpartial.json
wfdlogger/data/secstate.json
wfdlogger/data/settings.ui
wfdlogger/data/startup.ui
wfdlogger/data/wfd_preferences.json
wfdlogger/icon/cloud_green.png
wfdlogger/icon/cloud_grey.png
wfdlogger/icon/cloud_red.png
wfdlogger/icon/gear16x16.png
wfdlogger/icon/logo.png
wfdlogger/icon/radio_green.png
wfdlogger/icon/radio_grey.png
wfdlogger/icon/radio_red.png
wfdlogger/lib/__init__.py
wfdlogger/lib/cat_interface.py
wfdlogger/lib/cwinterface.py
wfdlogger/lib/database.py
wfdlogger/lib/lookup.py
wfdlogger/lib/n1mm.py
wfdlogger/lib/settings.py
wfdlogger/lib/version.py
wfdlogger/lib/versiontest.py
wfdlogger-24.2.19.dist-info/LICENSE
wfdlogger-24.2.19.dist-info/METADATA
wfdlogger-24.2.19.dist-info/WHEEL
wfdlogger-24.2.19.dist-info/entry_points.txt
wfdlogger-24.2.19.dist-info/top_level.txt
wfdlogger-24.2.19.dist-info/RECORD
