Metadata-Version: 2.1
Name: wfdlogger
Version: 24.2.19
Summary: Winter Field Day logger GUI
Author-email: Michael Bridak <michael.bridak@gmail.com>
Project-URL: Homepage, https://github.com/mbridak/WinterFieldDayLogger
Project-URL: Bug Tracker, https://github.com/mbridak/WinterFieldDayLogger/issues
Classifier: Programming Language :: Python :: 3
Classifier: Development Status :: 5 - Production/Stable
Classifier: License :: OSI Approved :: GNU General Public License v3 (GPLv3)
Classifier: Environment :: X11 Applications :: Qt
Classifier: Operating System :: POSIX :: Linux
Classifier: Intended Audience :: End Users/Desktop
Classifier: Natural Language :: English
Classifier: Topic :: Communications :: Ham Radio
Requires-Python: >=3.9
License-File: LICENSE
Requires-Dist: PyQt5
Requires-Dist: requests
Requires-Dist: dicttoxml
Requires-Dist: xmltodict
